client_pkg/__init__.py
client_pkg/client.py
chitChat_pkg_thutch97-0.2.0.dist-info/LICENSE
chitChat_pkg_thutch97-0.2.0.dist-info/METADATA
chitChat_pkg_thutch97-0.2.0.dist-info/WHEEL
chitChat_pkg_thutch97-0.2.0.dist-info/top_level.txt
chitChat_pkg_thutch97-0.2.0.dist-info/RECORD
